[
  {
    "word": "ring",
    "upVotes": 38,
    "downVotes": 1
  },
  {
    "word": "set",
    "upVotes": 30,
    "downVotes": 3
  },
  {
    "word": "clique",
    "upVotes": 28,
    "downVotes": 1
  },
  {
    "word": "group",
    "upVotes": 26,
    "downVotes": 1
  },
  {
    "word": "coterie",
    "upVotes": 26,
    "downVotes": 2
  },
  {
    "word": "company",
    "upVotes": 25,
    "downVotes": 2
  },
  {
    "word": "band",
    "upVotes": 22,
    "downVotes": 1
  },
  {
    "word": "encircle",
    "upVotes": 22,
    "downVotes": 1
  },
  {
    "word": "orbit",
    "upVotes": 22,
    "downVotes": 1
  },
  {
    "word": "crowd",
    "upVotes": 20,
    "downVotes": 1
  },
  {
    "word": "round",
    "upVotes": 20,
    "downVotes": 1
  },
  {
    "word": "society",
    "upVotes": 20,
    "downVotes": 1
  },
  {
    "word": "turn",
    "upVotes": 19,
    "downVotes": 1
  },
  {
    "word": "wheel",
    "upVotes": 19,
    "downVotes": 1
  },
  {
    "word": "circuit",
    "upVotes": 19,
    "downVotes": 2
  },
  {
    "word": "gang",
    "upVotes": 18,
    "downVotes": 1
  },
  {
    "word": "surround",
    "upVotes": 18,
    "downVotes": 1
  },
  {
    "word": "cycle",
    "upVotes": 16,
    "downVotes": 1
  },
  {
    "word": "loop",
    "upVotes": 16,
    "downVotes": 1
  },
  {
    "word": "hoop",
    "upVotes": 15,
    "downVotes": 0
  }
]