[
  {
    "word": "authority",
    "upVotes": 0,
    "downVotes": 0
  },
  {
    "word": "brevet",
    "upVotes": 0,
    "downVotes": 0
  },
  {
    "word": "bull",
    "upVotes": 0,
    "downVotes": 0
  },
  {
    "word": "citation",
    "upVotes": 0,
    "downVotes": 0
  },
  {
    "word": "decretal",
    "upVotes": 0,
    "downVotes": 0
  },
  {
    "word": "dispensation",
    "upVotes": 0,
    "downVotes": 0
  },
  {
    "word": "edict",
    "upVotes": 0,
    "downVotes": 0
  },
  {
    "word": "firman",
    "upVotes": 0,
    "downVotes": 0
  },
  {
    "word": "firmans",
    "upVotes": 0,
    "downVotes": 0
  },
  {
    "word": "firms",
    "upVotes": 0,
    "downVotes": 0
  },
  {
    "word": "hangs",
    "upVotes": 0,
    "downVotes": 0
  },
  {
    "word": "interpellation",
    "upVotes": 0,
    "downVotes": 0
  },
  {
    "word": "mandamus",
    "upVotes": 0,
    "downVotes": 0
  },
  {
    "word": "ordination",
    "upVotes": 0,
    "downVotes": 0
  },
  {
    "word": "precept",
    "upVotes": 0,
    "downVotes": 0
  },
  {
    "word": "prescription",
    "upVotes": 0,
    "downVotes": 0
  },
  {
    "word": "sanction",
    "upVotes": 0,
    "downVotes": 0
  },
  {
    "word": "warrant",
    "upVotes": 0,
    "downVotes": 0
  },
  {
    "word": "writ",
    "upVotes": 0,
    "downVotes": 0
  }
]