[
  {
    "word": "tool",
    "upVotes": 25,
    "downVotes": 2
  },
  {
    "word": "device",
    "upVotes": 23,
    "downVotes": 1
  },
  {
    "word": "utensil",
    "upVotes": 22,
    "downVotes": 0
  },
  {
    "word": "mechanism",
    "upVotes": 22,
    "downVotes": 1
  },
  {
    "word": "implement",
    "upVotes": 20,
    "downVotes": 0
  },
  {
    "word": "apparatus",
    "upVotes": 19,
    "downVotes": 0
  },
  {
    "word": "contrivance",
    "upVotes": 18,
    "downVotes": 0
  },
  {
    "word": "appliance",
    "upVotes": 17,
    "downVotes": 0
  },
  {
    "word": "machine",
    "upVotes": 17,
    "downVotes": 1
  },
  {
    "word": "gadget",
    "upVotes": 16,
    "downVotes": 0
  },
  {
    "word": "means",
    "upVotes": 16,
    "downVotes": 0
  },
  {
    "word": "vehicle",
    "upVotes": 15,
    "downVotes": 0
  },
  {
    "word": "agency",
    "upVotes": 14,
    "downVotes": 0
  },
  {
    "word": "contraption",
    "upVotes": 12,
    "downVotes": 0
  },
  {
    "word": "organ",
    "upVotes": 12,
    "downVotes": 0
  },
  {
    "word": "agent",
    "upVotes": 11,
    "downVotes": 0
  },
  {
    "word": "document",
    "upVotes": 11,
    "downVotes": 0
  },
  {
    "word": "equipment",
    "upVotes": 11,
    "downVotes": 0
  },
  {
    "word": "gizmo",
    "upVotes": 11,
    "downVotes": 0
  },
  {
    "word": "factor",
    "upVotes": 10,
    "downVotes": 0
  }
]