[
  {
    "word": "discover",
    "upVotes": 32,
    "downVotes": 2
  },
  {
    "word": "understand",
    "upVotes": 27,
    "downVotes": 1
  },
  {
    "word": "ascertain",
    "upVotes": 19,
    "downVotes": 0
  },
  {
    "word": "find out",
    "upVotes": 19,
    "downVotes": 0
  },
  {
    "word": "determine",
    "upVotes": 19,
    "downVotes": 1
  },
  {
    "word": "hear",
    "upVotes": 20,
    "downVotes": 3
  },
  {
    "word": "study",
    "upVotes": 17,
    "downVotes": 0
  },
  {
    "word": "memorize",
    "upVotes": 16,
    "downVotes": 0
  },
  {
    "word": "pick up",
    "upVotes": 14,
    "downVotes": 0
  },
  {
    "word": "read",
    "upVotes": 14,
    "downVotes": 0
  },
  {
    "word": "master",
    "upVotes": 13,
    "downVotes": 0
  },
  {
    "word": "get",
    "upVotes": 14,
    "downVotes": 2
  },
  {
    "word": "see",
    "upVotes": 12,
    "downVotes": 1
  },
  {
    "word": "detect",
    "upVotes": 11,
    "downVotes": 1
  },
  {
    "word": "unearth",
    "upVotes": 11,
    "downVotes": 1
  },
  {
    "word": "know",
    "upVotes": 10,
    "downVotes": 1
  },
  {
    "word": "glean",
    "upVotes": 9,
    "downVotes": 0
  },
  {
    "word": "grasp",
    "upVotes": 9,
    "downVotes": 0
  },
  {
    "word": "con",
    "upVotes": 9,
    "downVotes": 1
  },
  {
    "word": "gather",
    "upVotes": 9,
    "downVotes": 1
  }
]