[
  {
    "word": "gecko",
    "upVotes": 18,
    "downVotes": 3
  },
  {
    "word": "reptile",
    "upVotes": 14,
    "downVotes": 2
  },
  {
    "word": "chameleon",
    "upVotes": 10,
    "downVotes": 3
  },
  {
    "word": "reptilian",
    "upVotes": 8,
    "downVotes": 2
  },
  {
    "word": "dragon",
    "upVotes": 7,
    "downVotes": 1
  },
  {
    "word": "iguana",
    "upVotes": 7,
    "downVotes": 2
  },
  {
    "word": "agamid",
    "upVotes": 6,
    "downVotes": 2
  },
  {
    "word": "saurian",
    "upVotes": 6,
    "downVotes": 2
  },
  {
    "word": "lizards",
    "upVotes": 7,
    "downVotes": 4
  },
  {
    "word": "diamondback",
    "upVotes": 6,
    "downVotes": 3
  },
  {
    "word": "tortoise",
    "upVotes": 6,
    "downVotes": 3
  },
  {
    "word": "gigolo",
    "upVotes": 5,
    "downVotes": 2
  },
  {
    "word": "purse",
    "upVotes": 4,
    "downVotes": 1
  },
  {
    "word": "lounge lizard",
    "upVotes": 5,
    "downVotes": 3
  },
  {
    "word": "billfold",
    "upVotes": 2,
    "downVotes": 0
  },
  {
    "word": "carryall",
    "upVotes": 2,
    "downVotes": 0
  },
  {
    "word": "handbag",
    "upVotes": 2,
    "downVotes": 0
  },
  {
    "word": "hide",
    "upVotes": 2,
    "downVotes": 0
  },
  {
    "word": "lazybones",
    "upVotes": 2,
    "downVotes": 0
  },
  {
    "word": "legless lizard",
    "upVotes": 2,
    "downVotes": 0
  }
]