[
  {
    "word": "pin",
    "upVotes": 26,
    "downVotes": 1
  },
  {
    "word": "tack",
    "upVotes": 21,
    "downVotes": 1
  },
  {
    "word": "spike",
    "upVotes": 18,
    "downVotes": 1
  },
  {
    "word": "catch",
    "upVotes": 15,
    "downVotes": 0
  },
  {
    "word": "hook",
    "upVotes": 15,
    "downVotes": 0
  },
  {
    "word": "nab",
    "upVotes": 15,
    "downVotes": 0
  },
  {
    "word": "rivet",
    "upVotes": 15,
    "downVotes": 0
  },
  {
    "word": "secure",
    "upVotes": 14,
    "downVotes": 0
  },
  {
    "word": "peg",
    "upVotes": 14,
    "downVotes": 1
  },
  {
    "word": "collar",
    "upVotes": 13,
    "downVotes": 0
  },
  {
    "word": "apprehend",
    "upVotes": 11,
    "downVotes": 0
  },
  {
    "word": "capture",
    "upVotes": 11,
    "downVotes": 0
  },
  {
    "word": "fix",
    "upVotes": 11,
    "downVotes": 0
  },
  {
    "word": "arrest",
    "upVotes": 10,
    "downVotes": 0
  },
  {
    "word": "attach",
    "upVotes": 10,
    "downVotes": 0
  },
  {
    "word": "bolt",
    "upVotes": 10,
    "downVotes": 0
  },
  {
    "word": "fasten",
    "upVotes": 10,
    "downVotes": 0
  },
  {
    "word": "get",
    "upVotes": 10,
    "downVotes": 0
  },
  {
    "word": "join",
    "upVotes": 10,
    "downVotes": 0
  },
  {
    "word": "seize",
    "upVotes": 10,
    "downVotes": 0
  }
]