[
  {
    "word": "show",
    "upVotes": 22,
    "downVotes": 0
  },
  {
    "word": "display",
    "upVotes": 14,
    "downVotes": 0
  },
  {
    "word": "spectacle",
    "upVotes": 13,
    "downVotes": 0
  },
  {
    "word": "exposition",
    "upVotes": 11,
    "downVotes": 0
  },
  {
    "word": "pageantry",
    "upVotes": 11,
    "downVotes": 0
  },
  {
    "word": "parade",
    "upVotes": 10,
    "downVotes": 0
  },
  {
    "word": "extravaganza",
    "upVotes": 9,
    "downVotes": 0
  },
  {
    "word": "pomp",
    "upVotes": 9,
    "downVotes": 0
  },
  {
    "word": "exhibition",
    "upVotes": 8,
    "downVotes": 0
  },
  {
    "word": "scene",
    "upVotes": 8,
    "downVotes": 0
  },
  {
    "word": "array",
    "upVotes": 7,
    "downVotes": 0
  },
  {
    "word": "gala",
    "upVotes": 7,
    "downVotes": 0
  },
  {
    "word": "procession",
    "upVotes": 7,
    "downVotes": 0
  },
  {
    "word": "ceremony",
    "upVotes": 6,
    "downVotes": 0
  },
  {
    "word": "demonstration",
    "upVotes": 6,
    "downVotes": 0
  },
  {
    "word": "manifestation",
    "upVotes": 6,
    "downVotes": 0
  },
  {
    "word": "ostentation",
    "upVotes": 6,
    "downVotes": 0
  },
  {
    "word": "presentation",
    "upVotes": 6,
    "downVotes": 0
  },
  {
    "word": "sight",
    "upVotes": 6,
    "downVotes": 0
  },
  {
    "word": "celebration",
    "upVotes": 5,
    "downVotes": 0
  }
]