[
  {
    "word": "pilfer",
    "upVotes": 11,
    "downVotes": 1
  },
  {
    "word": "laurel",
    "upVotes": 10,
    "downVotes": 0
  },
  {
    "word": "filch",
    "upVotes": 10,
    "downVotes": 1
  },
  {
    "word": "medal",
    "upVotes": 10,
    "downVotes": 1
  },
  {
    "word": "steal",
    "upVotes": 10,
    "downVotes": 1
  },
  {
    "word": "ribbon",
    "upVotes": 9,
    "downVotes": 1
  },
  {
    "word": "feel",
    "upVotes": 8,
    "downVotes": 0
  },
  {
    "word": "garland",
    "upVotes": 8,
    "downVotes": 0
  },
  {
    "word": "handle",
    "upVotes": 8,
    "downVotes": 0
  },
  {
    "word": "trophy",
    "upVotes": 8,
    "downVotes": 0
  },
  {
    "word": "wreath",
    "upVotes": 8,
    "downVotes": 0
  },
  {
    "word": "decoration",
    "upVotes": 8,
    "downVotes": 1
  },
  {
    "word": "swipe",
    "upVotes": 8,
    "downVotes": 1
  },
  {
    "word": "appropriate",
    "upVotes": 7,
    "downVotes": 0
  },
  {
    "word": "crown",
    "upVotes": 7,
    "downVotes": 0
  },
  {
    "word": "embezzle",
    "upVotes": 7,
    "downVotes": 0
  },
  {
    "word": "hand",
    "upVotes": 7,
    "downVotes": 0
  },
  {
    "word": "lift",
    "upVotes": 7,
    "downVotes": 0
  },
  {
    "word": "paw",
    "upVotes": 7,
    "downVotes": 0
  },
  {
    "word": "pinch",
    "upVotes": 7,
    "downVotes": 0
  }
]