[
  {
    "word": "bridge",
    "upVotes": 6,
    "downVotes": 0
  },
  {
    "word": "blackjack",
    "upVotes": 5,
    "downVotes": 0
  },
  {
    "word": "fire hook",
    "upVotes": 5,
    "downVotes": 0
  },
  {
    "word": "salamander",
    "upVotes": 5,
    "downVotes": 0
  },
  {
    "word": "spit",
    "upVotes": 4,
    "downVotes": 0
  },
  {
    "word": "stove poker",
    "upVotes": 4,
    "downVotes": 0
  },
  {
    "word": "andiron",
    "upVotes": 3,
    "downVotes": 0
  },
  {
    "word": "baccarat",
    "upVotes": 3,
    "downVotes": 0
  },
  {
    "word": "card game",
    "upVotes": 3,
    "downVotes": 0
  },
  {
    "word": "cribbage",
    "upVotes": 3,
    "downVotes": 0
  },
  {
    "word": "euchre",
    "upVotes": 3,
    "downVotes": 0
  },
  {
    "word": "game",
    "upVotes": 3,
    "downVotes": 0
  },
  {
    "word": "grate",
    "upVotes": 3,
    "downVotes": 0
  },
  {
    "word": "gridiron",
    "upVotes": 3,
    "downVotes": 0
  },
  {
    "word": "lotto",
    "upVotes": 3,
    "downVotes": 0
  },
  {
    "word": "patience",
    "upVotes": 3,
    "downVotes": 0
  },
  {
    "word": "pinochle",
    "upVotes": 3,
    "downVotes": 0
  },
  {
    "word": "poker game",
    "upVotes": 3,
    "downVotes": 0
  },
  {
    "word": "tongs",
    "upVotes": 3,
    "downVotes": 0
  },
  {
    "word": "trivet",
    "upVotes": 3,
    "downVotes": 0
  }
]