[
  {
    "word": "compliment",
    "upVotes": 43,
    "downVotes": 1
  },
  {
    "word": "acclaim",
    "upVotes": 39,
    "downVotes": 0
  },
  {
    "word": "laud",
    "upVotes": 32,
    "downVotes": 0
  },
  {
    "word": "glorify",
    "upVotes": 29,
    "downVotes": 0
  },
  {
    "word": "commendation",
    "upVotes": 29,
    "downVotes": 1
  },
  {
    "word": "extol",
    "upVotes": 26,
    "downVotes": 0
  },
  {
    "word": "commend",
    "upVotes": 25,
    "downVotes": 0
  },
  {
    "word": "applaud",
    "upVotes": 24,
    "downVotes": 0
  },
  {
    "word": "exalt",
    "upVotes": 23,
    "downVotes": 0
  },
  {
    "word": "honor",
    "upVotes": 23,
    "downVotes": 0
  },
  {
    "word": "applause",
    "upVotes": 22,
    "downVotes": 0
  },
  {
    "word": "honour",
    "upVotes": 22,
    "downVotes": 1
  },
  {
    "word": "worship",
    "upVotes": 22,
    "downVotes": 2
  },
  {
    "word": "homage",
    "upVotes": 20,
    "downVotes": 0
  },
  {
    "word": "acclamation",
    "upVotes": 19,
    "downVotes": 0
  },
  {
    "word": "approval",
    "upVotes": 19,
    "downVotes": 0
  },
  {
    "word": "approve",
    "upVotes": 19,
    "downVotes": 0
  },
  {
    "word": "eulogize",
    "upVotes": 19,
    "downVotes": 0
  },
  {
    "word": "glorification",
    "upVotes": 19,
    "downVotes": 0
  },
  {
    "word": "reverence",
    "upVotes": 19,
    "downVotes": 0
  }
]