[
  {
    "word": "navigation",
    "upVotes": 10,
    "downVotes": 0
  },
  {
    "word": "seafaring",
    "upVotes": 10,
    "downVotes": 0
  },
  {
    "word": "cruising",
    "upVotes": 8,
    "downVotes": 0
  },
  {
    "word": "nautical",
    "upVotes": 8,
    "downVotes": 0
  },
  {
    "word": "navigating",
    "upVotes": 8,
    "downVotes": 0
  },
  {
    "word": "boating",
    "upVotes": 7,
    "downVotes": 0
  },
  {
    "word": "glide",
    "upVotes": 7,
    "downVotes": 0
  },
  {
    "word": "gliding",
    "upVotes": 7,
    "downVotes": 0
  },
  {
    "word": "sailplaning",
    "upVotes": 7,
    "downVotes": 0
  },
  {
    "word": "soaring",
    "upVotes": 7,
    "downVotes": 0
  },
  {
    "word": "shipping",
    "upVotes": 6,
    "downVotes": 0
  },
  {
    "word": "maritime",
    "upVotes": 5,
    "downVotes": 0
  },
  {
    "word": "naval",
    "upVotes": 5,
    "downVotes": 0
  },
  {
    "word": "navigational",
    "upVotes": 5,
    "downVotes": 0
  },
  {
    "word": "pilotage",
    "upVotes": 5,
    "downVotes": 0
  },
  {
    "word": "piloting",
    "upVotes": 5,
    "downVotes": 0
  },
  {
    "word": "rowing",
    "upVotes": 5,
    "downVotes": 0
  },
  {
    "word": "voyaging",
    "upVotes": 5,
    "downVotes": 0
  },
  {
    "word": "yachting",
    "upVotes": 5,
    "downVotes": 0
  },
  {
    "word": "canoeing",
    "upVotes": 4,
    "downVotes": 0
  }
]