[
  {
    "word": "angel",
    "upVotes": 17,
    "downVotes": 1
  },
  {
    "word": "paragon",
    "upVotes": 13,
    "downVotes": 0
  },
  {
    "word": "hero",
    "upVotes": 14,
    "downVotes": 3
  },
  {
    "word": "ideal",
    "upVotes": 11,
    "downVotes": 0
  },
  {
    "word": "canonize",
    "upVotes": 11,
    "downVotes": 1
  },
  {
    "word": "holy man",
    "upVotes": 9,
    "downVotes": 0
  },
  {
    "word": "canonise",
    "upVotes": 8,
    "downVotes": 1
  },
  {
    "word": "apotheosis",
    "upVotes": 7,
    "downVotes": 0
  },
  {
    "word": "enshrine",
    "upVotes": 7,
    "downVotes": 0
  },
  {
    "word": "model",
    "upVotes": 7,
    "downVotes": 0
  },
  {
    "word": "martyr",
    "upVotes": 7,
    "downVotes": 1
  },
  {
    "word": "nonesuch",
    "upVotes": 7,
    "downVotes": 1
  },
  {
    "word": "nonpareil",
    "upVotes": 7,
    "downVotes": 1
  },
  {
    "word": "holy person",
    "upVotes": 6,
    "downVotes": 0
  },
  {
    "word": "nonsuch",
    "upVotes": 6,
    "downVotes": 0
  },
  {
    "word": "pietist",
    "upVotes": 6,
    "downVotes": 0
  },
  {
    "word": "apostle",
    "upVotes": 6,
    "downVotes": 1
  },
  {
    "word": "disciple",
    "upVotes": 5,
    "downVotes": 0
  },
  {
    "word": "hallow",
    "upVotes": 5,
    "downVotes": 0
  },
  {
    "word": "sainted",
    "upVotes": 5,
    "downVotes": 0
  }
]