[
  {
    "word": "mute",
    "upVotes": 37,
    "downVotes": 1
  },
  {
    "word": "quiet",
    "upVotes": 36,
    "downVotes": 2
  },
  {
    "word": "taciturn",
    "upVotes": 32,
    "downVotes": 1
  },
  {
    "word": "mum",
    "upVotes": 26,
    "downVotes": 1
  },
  {
    "word": "soundless",
    "upVotes": 23,
    "downVotes": 0
  },
  {
    "word": "still",
    "upVotes": 23,
    "downVotes": 0
  },
  {
    "word": "reserved",
    "upVotes": 23,
    "downVotes": 2
  },
  {
    "word": "noiseless",
    "upVotes": 20,
    "downVotes": 0
  },
  {
    "word": "hushed",
    "upVotes": 18,
    "downVotes": 0
  },
  {
    "word": "reticent",
    "upVotes": 18,
    "downVotes": 0
  },
  {
    "word": "tacit",
    "upVotes": 18,
    "downVotes": 0
  },
  {
    "word": "dumb",
    "upVotes": 19,
    "downVotes": 2
  },
  {
    "word": "uncommunicative",
    "upVotes": 16,
    "downVotes": 0
  },
  {
    "word": "voiceless",
    "upVotes": 16,
    "downVotes": 0
  },
  {
    "word": "close-mouthed",
    "upVotes": 15,
    "downVotes": 0
  },
  {
    "word": "speechless",
    "upVotes": 13,
    "downVotes": 0
  },
  {
    "word": "tight-lipped",
    "upVotes": 13,
    "downVotes": 1
  },
  {
    "word": "calm",
    "upVotes": 12,
    "downVotes": 0
  },
  {
    "word": "wordless",
    "upVotes": 12,
    "downVotes": 0
  },
  {
    "word": "close",
    "upVotes": 10,
    "downVotes": 0
  }
]