[
  {
    "word": "yield",
    "upVotes": 68,
    "downVotes": 1
  },
  {
    "word": "give up",
    "upVotes": 53,
    "downVotes": 0
  },
  {
    "word": "relinquish",
    "upVotes": 44,
    "downVotes": 0
  },
  {
    "word": "abandon",
    "upVotes": 37,
    "downVotes": 0
  },
  {
    "word": "cede",
    "upVotes": 35,
    "downVotes": 0
  },
  {
    "word": "resign",
    "upVotes": 35,
    "downVotes": 1
  },
  {
    "word": "renounce",
    "upVotes": 31,
    "downVotes": 0
  },
  {
    "word": "submit",
    "upVotes": 28,
    "downVotes": 0
  },
  {
    "word": "capitulate",
    "upVotes": 25,
    "downVotes": 0
  },
  {
    "word": "forgo",
    "upVotes": 23,
    "downVotes": 0
  },
  {
    "word": "waive",
    "upVotes": 23,
    "downVotes": 0
  },
  {
    "word": "abdicate",
    "upVotes": 22,
    "downVotes": 0
  },
  {
    "word": "capitulation",
    "upVotes": 22,
    "downVotes": 0
  },
  {
    "word": "resignation",
    "upVotes": 22,
    "downVotes": 0
  },
  {
    "word": "abandonment",
    "upVotes": 21,
    "downVotes": 0
  },
  {
    "word": "forsake",
    "upVotes": 21,
    "downVotes": 0
  },
  {
    "word": "give in",
    "upVotes": 20,
    "downVotes": 0
  },
  {
    "word": "hand over",
    "upVotes": 20,
    "downVotes": 0
  },
  {
    "word": "deliver",
    "upVotes": 19,
    "downVotes": 0
  },
  {
    "word": "let go",
    "upVotes": 19,
    "downVotes": 0
  }
]