[
  {
    "word": "gain",
    "upVotes": 35,
    "downVotes": 3
  },
  {
    "word": "get",
    "upVotes": 35,
    "downVotes": 3
  },
  {
    "word": "acquire",
    "upVotes": 34,
    "downVotes": 2
  },
  {
    "word": "obtain",
    "upVotes": 30,
    "downVotes": 2
  },
  {
    "word": "secure",
    "upVotes": 29,
    "downVotes": 1
  },
  {
    "word": "triumph",
    "upVotes": 29,
    "downVotes": 1
  },
  {
    "word": "earn",
    "upVotes": 26,
    "downVotes": 2
  },
  {
    "word": "procure",
    "upVotes": 26,
    "downVotes": 2
  },
  {
    "word": "succeed",
    "upVotes": 24,
    "downVotes": 0
  },
  {
    "word": "achieve",
    "upVotes": 21,
    "downVotes": 1
  },
  {
    "word": "attain",
    "upVotes": 20,
    "downVotes": 0
  },
  {
    "word": "conquer",
    "upVotes": 20,
    "downVotes": 0
  },
  {
    "word": "overcome",
    "upVotes": 18,
    "downVotes": 1
  },
  {
    "word": "take",
    "upVotes": 18,
    "downVotes": 1
  },
  {
    "word": "capture",
    "upVotes": 17,
    "downVotes": 0
  },
  {
    "word": "prevail",
    "upVotes": 15,
    "downVotes": 1
  },
  {
    "word": "victory",
    "upVotes": 15,
    "downVotes": 1
  },
  {
    "word": "realize",
    "upVotes": 14,
    "downVotes": 0
  },
  {
    "word": "score",
    "upVotes": 14,
    "downVotes": 0
  },
  {
    "word": "catch",
    "upVotes": 12,
    "downVotes": 0
  }
]